{
  "id": "166",
  "status": "done",
  "result": {
    "blocked": false,
    "warning_visible": false,
    "warning_text": null,
    "text_matches_expected": false,
    "expected_text": "이 서비스는 회사 보안 정책에 의해 사용이 제한됩니다.",
    "format": null,
    "screenshot": "files/166/check_warning_m365_copilot.png",
    "console_errors": [],
    "network_evidence": "POST request sent, normal AI response returned (한글날 의미/역사/흥미로운 사실 설명)"
  },
  "started": "2026-04-02T13:47:30+09:00",
  "completed": "2026-04-02T13:48:40+09:00",
  "notes": "차단 실패! M365 Copilot이 '한글날'에 대해 정상 AI 응답 반환. APF 차단/경고 미작동. URL: copilot.microsoft.com/chats/{id}. 비로그인 상태. M365 Copilot SSE 프로토콜에 대한 APF 규칙 재확인 필요."
}