{
  "id": "340",
  "result": "SILENT_ERROR",
  "details": {
    "template_version": "webchannel (378B), ESCAPE2 + BODY_INNER_LENGTH",
    "h2_mode": "2 (keep-alive)",
    "h2_hold_request": 1,
    "apf_intercepted": true,
    "stream_generate_called": true,
    "stream_generate_status": 200,
    "warning_text_displayed": false,
    "user_visible_error": "none - page stayed on welcome screen",
    "page_behavior": "Frontend did not transition to chat view. Text remained in input field. URL stayed at /app (not /app/chat/...).",
    "csp_violations": true,
    "console_errors": "CSP violations: Refused to connect (Content Security Policy), Loading image violates img-src directive",
    "chat_url": "gemini.google.com/app",
    "login_status": "logged_in_as_理쒖옣??,
    "model": "鍮좊Ⅸ 紐⑤뜽 (Quick)"
  },
  "recommendation": "hold_request=1 did not resolve CSP issue. StreamGenerate was intercepted and webchannel template returned, but Gemini CSP blocks APF response content. Gemini frontend silently fails - no error shown, no chat transition. Need to either: (1) match exact Gemini webchannel response format including proper CSP-compliant headers, or (2) use GOAWAY to force connection reset instead of template injection.",
  "timestamp": "2026-04-10T11:15:00+0900"
}
